scripts/__init__.py
scripts/ana_solution.py
scripts/ana_solvent.py
scripts/ana_trajectory.py
scripts/bash_cli.py
scripts/convert_aa2cg.py
scripts/densities.py
scripts/dlm_ana_density.py
scripts/dlm_ana_gyration.py
scripts/dlm_ana_solvation.py
scripts/dlm_atoms2beads.py
scripts/dlm_equilibrate.py
scripts/dlm_production_run.py
scripts/dlm_solvate.py
scripts/dlm_visualise_dcd.py
scripts/dlm_visualise_vmd.py
scripts/gmx-add-ions-solv.bsh
scripts/gmx-ana-clusters-for.bsh
scripts/gmx-ana-clusters-prl.bsh
scripts/gmx-ana-clusters.bsh
scripts/gmx-ana-gyration-dirs.bsh
scripts/gmx-ana-gyration-pieces.bsh
scripts/gmx-ana-gyration.bsh
scripts/gmx-ana-maxclust-for.bsh
scripts/gmx-ana-solvation.bsh
scripts/gmx-center-cluster.bsh
scripts/gmx-equilibrate.bsh
scripts/gmx-posres-gro.bsh
scripts/gmx-setup-equil.bsh
scripts/gmx-setup-multi.bsh
scripts/namd_bilayer_calculate_ndens_sld.py
scripts/namd_bilayer_postprocessing.py
scripts/namd_setup_equil.py
scripts/namd_setup_psf.py
scripts/namd_solvate.py
scripts/shape_structure.py
scripts/smiles.py
shapes/__init__.py
shapes/basics/__init__.py
shapes/basics/defaults.py
shapes/basics/functions.py
shapes/basics/globals.py
shapes/basics/help.py
shapes/basics/input.py
shapes/basics/mendeleyev.py
shapes/basics/options.py
shapes/basics/temp.yaml
shapes/basics/utils.py
shapes/cgmap/__init__.py
shapes/cgmap/coarse_grainer.py
shapes/cgmap/martini_converter.py
shapes/cgmap/molecule_mapper.py
shapes/designs/__init__.py
shapes/designs/protolattice.py
shapes/designs/protolayer.py
shapes/designs/protoshape.py
shapes/designs/smiles.py
shapes/ioports/__init__.py
shapes/ioports/ioconfig.py
shapes/ioports/iodcd.py
shapes/ioports/iofield.py
shapes/ioports/iofiles.py
shapes/ioports/ioframe.py
shapes/ioports/iogro.py
shapes/ioports/iohistory.py
shapes/ioports/iopdb.py
shapes/ioports/iotop.py
shapes/ioports/iotraj.py
shapes/ioports/ioxyz.py
shapes/models/__init__.py
shapes/models/topology.py
shapes/project/__init__.py
shapes/project/analysis.py
shapespyer-0.2.4.dist-info/METADATA
shapespyer-0.2.4.dist-info/WHEEL
shapespyer-0.2.4.dist-info/entry_points.txt
shapespyer-0.2.4.dist-info/licenses/LICENSE
shapespyer-0.2.4.dist-info/RECORD
