Metadata-Version: 2.4
Name: Shapespyer
Version: 0.2.4
Summary: Python toolkit for generation and equilibration of complex soft matter systems
Project-URL: Homepage, https://gitlab.com/simnavi/shapespyer
Project-URL: Repository, https://gitlab.com/simnavi/shapespyer.git
Author-email: Andrey Brukhno <andrey.brukhno@stfc.ac.uk>, Michael Seatom <michael.seaton@stfc.ac.uk>, Valeria Losasso <valeria.losasso@stfc.ac.uk>, Mariam Demir <mariam.demir@stfc.ac.uk>, Saul Beck <saul.beck@stfc.ac.uk>, Ales Kutsepau <ales.kutsepau@ess.eu>
License-File: LICENSE
Classifier: Development Status :: 4 - Beta
Classifier: Intended Audience :: Science/Research
Classifier: Programming Language :: Python
Classifier: Programming Language :: Python :: 3 :: Only
Classifier: Topic :: Scientific/Engineering
Requires-Python: >=3.10
Requires-Dist: docopt>=0.6.2
Requires-Dist: matplotlib>=3.8
Requires-Dist: numpy>=2.0.2
Requires-Dist: pandas>=2.3.0
Requires-Dist: platformdirs>=4.3.8
Requires-Dist: pooch>=1.8.2
Requires-Dist: psutil>=7.0.0
Requires-Dist: pyyaml>=6.0.2
Requires-Dist: scipy>=1.15.3
Requires-Dist: tqdm>=4.67.1
Requires-Dist: typeguard>=4.4.4
Provides-Extra: extras
Requires-Dist: ipywidgets>=8.1.7; extra == 'extras'
Requires-Dist: jupyter>=1.1.1; extra == 'extras'
Requires-Dist: mdtraj; extra == 'extras'
Requires-Dist: nglview>3.1.4; extra == 'extras'
